akeyless/__init__.py
akeyless/api_client.py
akeyless/api_response.py
akeyless/configuration.py
akeyless/exceptions.py
akeyless/py.typed
akeyless/rest.py
akeyless/api/__init__.py
akeyless/api/v2_api.py
akeyless/models/__init__.py
akeyless/models/access_or_group_permission_assignment.py
akeyless/models/access_permission_assignment.py
akeyless/models/account_custom_field_create.py
akeyless/models/account_custom_field_create_output.py
akeyless/models/account_custom_field_delete.py
akeyless/models/account_custom_field_get.py
akeyless/models/account_custom_field_get_output.py
akeyless/models/account_custom_field_list.py
akeyless/models/account_custom_field_update.py
akeyless/models/account_general_settings.py
akeyless/models/account_object_version_settings_output.py
akeyless/models/acme_account.py
akeyless/models/active_directory_migration.py
akeyless/models/active_directory_payload.py
akeyless/models/add_gateway_allowed_access_id.py
akeyless/models/admins_config_part.py
akeyless/models/ai_insights_config_part.py
akeyless/models/ai_insights_setting.py
akeyless/models/akeyless_gateway_config.py
akeyless/models/alias_details.py
akeyless/models/alias_details_output.py
akeyless/models/all_analytics_data.py
akeyless/models/allowed_access.py
akeyless/models/allowed_access_args.py
akeyless/models/allowed_access_delete_args.py
akeyless/models/allowed_access_old.py
akeyless/models/allowed_access_update_args.py
akeyless/models/allowed_client_type.py
akeyless/models/allowed_ip_settings.py
akeyless/models/api_key_access_rules.py
akeyless/models/artifactory_target_details.py
akeyless/models/assoc_role_auth_method.py
akeyless/models/assoc_target_item.py
akeyless/models/attribute_type_and_value.py
akeyless/models/auth.py
akeyless/models/auth_expiration_event.py
akeyless/models/auth_method.py
akeyless/models/auth_method_access_info.py
akeyless/models/auth_method_additional_data.py
akeyless/models/auth_method_create_api_key.py
akeyless/models/auth_method_create_aws_iam.py
akeyless-5.0.20.dist-info/licenses/LICENSE
akeyless-5.0.20.dist-info/METADATA
akeyless-5.0.20.dist-info/WHEEL
akeyless-5.0.20.dist-info/top_level.txt
akeyless-5.0.20.dist-info/RECORD
