Metadata-Version: 2.4
Name: akeyless
Version: 5.0.20
Summary: Akeyless API
Home-page: https://www.akeyless.io/
Author: Akeyless
Author-email: support@akeyless.io
Keywords: OpenAPI,OpenAPI-Generator,Akeyless API
License-File: LICENSE
Requires-Dist: urllib3>=2.1.0
Requires-Dist: six>=1.10
Requires-Dist: certifi
Requires-Dist: python-dateutil
Requires-Dist: psutil>=7.0.0
Dynamic: author
Dynamic: author-email
Dynamic: description
Dynamic: home-page
Dynamic: keywords
Dynamic: license-file
Dynamic: requires-dist
Dynamic: summary
